model/__init__.py
model/dto.py
model/models.py
repository/__init__.py
repository/base.py
service/__init__.py
service/base.py
util/__init__.py
util/database.py
model_pessoasenderecos_lib-0.1.2.dist-info/METADATA
model_pessoasenderecos_lib-0.1.2.dist-info/WHEEL
model_pessoasenderecos_lib-0.1.2.dist-info/top_level.txt
model_pessoasenderecos_lib-0.1.2.dist-info/RECORD
